LICENSE
MANIFEST.in
README.rst
setup.py
hydra_agent/__init__.py
hydra_agent/__version__.py
hydra_agent/main.py
hydra_agent.egg-info/PKG-INFO
hydra_agent.egg-info/SOURCES.txt
hydra_agent.egg-info/dependency_links.txt
hydra_agent.egg-info/entry_points.txt
hydra_agent.egg-info/requires.txt
hydra_agent.egg-info/top_level.txt
hydra_agent.egg-info/zip-safe
hydra_agent/api/__init__.py
hydra_agent/api/main.py
hydra_agent/api/routes.py
hydra_agent/api/handler/__init__.py
hydra_agent/api/handler/backup.py
hydra_agent/api/handler/base.py
hydra_agent/api/handler/cluster.py
hydra_agent/api/handler/heartbeat.py
hydra_agent/api/handler/infobase.py
hydra_agent/api/handler/license.py
hydra_agent/api/handler/session.py
hydra_agent/config/__init__.py
hydra_agent/config/api_config.py
hydra_agent/config/base_config.py
hydra_agent/config/config.py
hydra_agent/config/postgresql_config.py
hydra_agent/config/rac_config.py
hydra_agent/config/ring_config.py
hydra_agent/config/v8_config.py
hydra_agent/db/__init__.py
hydra_agent/db/postgresql/__init__.py
hydra_agent/db/postgresql/postgresql.py
hydra_agent/rac/__init__.py
hydra_agent/rac/rac.py
hydra_agent/rac/cluster_manager/__init__.py
hydra_agent/rac/cluster_manager/cluster.py
hydra_agent/rac/cluster_manager/cluster_manager.py
hydra_agent/rac/cluster_manager/load_balancing_mode.py
hydra_agent/rac/cluster_manager/security_level.py
hydra_agent/rac/infobase_manager/__init__.py
hydra_agent/rac/infobase_manager/infobase.py
hydra_agent/rac/infobase_manager/infobase_manager.py
hydra_agent/rac/session_manager/__init__.py
hydra_agent/rac/session_manager/session.py
hydra_agent/rac/session_manager/session_manager.py
hydra_agent/ring/__init__.py
hydra_agent/ring/ring.py
hydra_agent/ring/license_manager/__init__.py
hydra_agent/ring/license_manager/license_manager.py
hydra_agent/utils/__init__.py
hydra_agent/utils/system.py
hydra_agent/v8/__init__.py
hydra_agent/v8/connection_string.py
hydra_agent/v8/file_connection_string.py
hydra_agent/v8/server_connection_string.py
hydra_agent/v8/v8.py