Metadata-Version: 1.2
Name: hydra-agent
Version: 0.0.12
Summary: Cross-platform remote administration agent for 1C:Enterprise
Home-page: https://github.com/vbondarevsky/hydra_agent
Author: Vladimir Bondarevskiy
Author-email: vbondarevsky@gmail.com
License: https://www.gnu.org/licenses/gpl-3.0
Platform: UNKNOWN
Classifier: Development Status :: 1 - Planning
Classifier: License :: OSI Approved :: GNU General Public License v3 (GPLv3)
Classifier: Programming Language :: Python :: 3.6
Classifier: Programming Language :: Python :: 3.7
Classifier: Programming Language :: Python :: Implementation :: CPython
Requires-Python: >=3
